LICENCE
MANIFEST.in
README.md
package.json
setup.py
django_s3direct.egg-info/PKG-INFO
django_s3direct.egg-info/SOURCES.txt
django_s3direct.egg-info/dependency_links.txt
django_s3direct.egg-info/not-zip-safe
django_s3direct.egg-info/requires.txt
django_s3direct.egg-info/top_level.txt
s3direct/__init__.py
s3direct/fields.py
s3direct/tests.py
s3direct/urls.py
s3direct/utils.py
s3direct/views.py
s3direct/widgets.py
s3direct/__pycache__/__init__.cpython-310.pyc
s3direct/__pycache__/fields.cpython-310.pyc
s3direct/__pycache__/tests.cpython-310.pyc
s3direct/__pycache__/urls.cpython-310.pyc
s3direct/__pycache__/utils.cpython-310.pyc
s3direct/__pycache__/views.cpython-310.pyc
s3direct/__pycache__/widgets.cpython-310.pyc
s3direct/static/s3direct/dist/.gitignore
s3direct/static/s3direct/dist/glyphicons-halflings-white.c1b68cdf.png
s3direct/static/s3direct/dist/glyphicons-halflings-white.da002663.png
s3direct/static/s3direct/dist/glyphicons-halflings.03b4543b.png
s3direct/static/s3direct/dist/glyphicons-halflings.21499243.png
s3direct/static/s3direct/dist/index.css
s3direct/static/s3direct/dist/index.css.map
s3direct/static/s3direct/dist/index.js
s3direct/static/s3direct/dist/index.js.map
s3direct/templates/s3direct/s3direct-widget.tpl