Metadata-Version: 2.1
Name: django-s3direct
Version: 2.0.3
Summary: Add direct uploads to S3 functionality with a progress bar to file input fields.
Home-page: https://github.com/bradleyg/django-s3direct#readme
Author: Bradley Griffiths
Author-email: bradley.griffiths@gmail.com
License: UNKNOWN
Platform: UNKNOWN
Classifier: Development Status :: 4 - Beta
Classifier: Environment :: Web Environment
Classifier: Framework :: Django
Classifier: Intended Audience :: Developers
Classifier: License :: OSI Approved :: MIT License
Classifier: Operating System :: OS Independent
Classifier: Programming Language :: Python :: 3.4
Classifier: Programming Language :: Python :: 3.5
Classifier: Programming Language :: Python :: 3.6
License-File: LICENCE
